padrelay/__init__.py
padrelay/client/__init__.py
padrelay/client/client_app.py
padrelay/client/constants.py
padrelay/client/input.py
padrelay/core/__init__.py
padrelay/core/config.py
padrelay/core/exceptions.py
padrelay/core/logging_utils.py
padrelay/protocol/__init__.py
padrelay/protocol/constants.py
padrelay/protocol/messages.py
padrelay/protocol/tcp.py
padrelay/protocol/udp.py
padrelay/scripts/__init__.py
padrelay/scripts/client.py
padrelay/scripts/key_mapper.py
padrelay/scripts/server.py
padrelay/security/__init__.py
padrelay/security/auth.py
padrelay/security/password_strength.py
padrelay/security/rate_limiting.py
padrelay/security/tls_utils.py
padrelay/server/__init__.py
padrelay/server/constants.py
padrelay/server/input_processor.py
padrelay/server/server_app.py
padrelay/server/virtual_gamepad.py
padrelay-1.1.0.dist-info/licenses/LICENSE
padrelay-1.1.0.dist-info/METADATA
padrelay-1.1.0.dist-info/WHEEL
padrelay-1.1.0.dist-info/entry_points.txt
padrelay-1.1.0.dist-info/top_level.txt
padrelay-1.1.0.dist-info/RECORD
