Metadata-Version: 2.4
Name: padrelay
Version: 1.1.0
Summary: A client-server application for transmitting gamepad input over a network
Author-email: ssh-den <sshden@duck.com>
License-Expression: MIT
Project-URL: Homepage, https://github.com/ssh-den/PadRelay
Classifier: Development Status :: 4 - Beta
Classifier: Environment :: Console
Classifier: Intended Audience :: End Users/Desktop
Classifier: Operating System :: OS Independent
Classifier: Programming Language :: Python :: 3
Classifier: Programming Language :: Python :: 3.6
Classifier: Programming Language :: Python :: 3.7
Classifier: Programming Language :: Python :: 3.8
Classifier: Programming Language :: Python :: 3.9
Classifier: Topic :: Games/Entertainment
Requires-Python: >=3.6
License-File: LICENSE
Requires-Dist: pygame
Provides-Extra: server
Requires-Dist: vgamepad; extra == "server"
Dynamic: license-file
